leipy/__init__.py
leipy/gleif.py
leipy-0.1.0.dist-info/LICENSE.txt
leipy-0.1.0.dist-info/METADATA
leipy-0.1.0.dist-info/RECORD
leipy-0.1.0.dist-info/WHEEL
leipy-0.1.0.dist-info/top_level.txt
