Metadata-Version: 2.1
Name: leipy
Version: 0.1.0
Summary: A python wrapper / client for GLEIF public API.
Home-page: https://github.com/emredjan/leipy
Author: emredjan
Author-email: emredjan@gmail.com
License: MIT
Keywords: lei gleif api api-wrapper
Platform: UNKNOWN
Classifier: Development Status :: 3 - Alpha
Classifier: Intended Audience :: Developers
Classifier: Topic :: Office/Business :: Financial
Classifier: License :: OSI Approved :: MIT License
Classifier: Programming Language :: Python :: 3
Classifier: Programming Language :: Python :: 3.4
Classifier: Programming Language :: Python :: 3.5
Classifier: Programming Language :: Python :: 3.6
Requires-Python: >=3.4
Requires-Dist: requests
Requires-Dist: python-dateutil
